asyncrun/__init__.py
asyncrun/core.py
asyncrun-0.3.0.dist-info/LICENSE
asyncrun-0.3.0.dist-info/METADATA
asyncrun-0.3.0.dist-info/WHEEL
asyncrun-0.3.0.dist-info/top_level.txt
asyncrun-0.3.0.dist-info/RECORD
